{
  "id": "into-the-meadow-dsk-registry",
  "version": "0.1.0",
  "rule": "Game-specific DSKs live here; reusable meadow infrastructure stays in ProtoKits.",
  "external": ["meadow-area-kit", "meadow-webgl-render-kit"],
  "local": [
    "into-the-meadow-game-dsk",
    "web-host-dsk",
    "game-composition-dsk",
    "meadow-area-bridge-dsk",
    "meadow-terrain-texture-dsk",
    "path-corridor-dsk",
    "grass-patch-dsk",
    "gpu-grass-render-dsk",
    "wind-field-dsk",
    "tree-object-dsk",
    "meadow-scatter-dsk",
    "meadow-atmosphere-dsk",
    "meadow-player-dsk",
    "meadow-camera-dsk",
    "meadow-input-dsk",
    "meadow-interaction-dsk",
    "meadow-story-dsk",
    "meadow-objective-dsk",
    "meadow-ecology-dsk",
    "meadow-audio-dsk",
    "meadow-ui-dsk",
    "meadow-save-dsk",
    "meadow-diagnostics-dsk",
    "meadow-performance-dsk",
    "meadow-render-host-dsk",
    "static-pages-deploy-dsk"
  ],
  "requiredForV01": [
    "into-the-meadow-game-dsk",
    "web-host-dsk",
    "game-composition-dsk",
    "meadow-area-bridge-dsk",
    "meadow-render-host-dsk",
    "meadow-diagnostics-dsk",
    "static-pages-deploy-dsk"
  ],
  "phases": {
    "v0.1": "bootable DSK scaffold and browser meadow proof",
    "v0.2": "first-person exploration, camera, input, interaction, story, objectives",
    "v0.3": "grass patches, shader wind, terrain texture extraction, performance profiles"
  }
}
